setup.cfg
setup.py
scrapy_lambda.egg-info/PKG-INFO
scrapy_lambda.egg-info/SOURCES.txt
scrapy_lambda.egg-info/dependency_links.txt
scrapy_lambda.egg-info/requires.txt
scrapy_lambda.egg-info/top_level.txt
scrapylambda/__init__.py
scrapylambda/scrapylambda.py