Metadata-Version: 1.0
Name: scrapy-lambda
Version: 0.1.0
Summary: Scrapy pipeline which invokes a lambda with the scraped item
Home-page: https://github.com/suraj-arya/scrapy-lambda
Author: Suraj Arya
Author-email: suraj@loanzen.in
License: MIT license
Keywords: scrapy-lambda
Platform: UNKNOWN
